[
    {
        "id": 1,
        "name": "Kerajinan Tangan Resin",
        "price": {
            "oldPrice": 40000,
            "newPrice": 35000,
            "product-description": ""
        },
        "rating" : 5,
        "discount": 5,
        "img": {
            "singleImage": "img/products/kerajinan/kerajinan tangan resin.jpg",
            "thumbs": [
                "img/products/kerajinan/kerajinan tangan resin.jpg",
                "img/products/kerajinan/kerajinan tangan resin.jpg",
                "img/products/kerajinan/kerajinan tangan resin.jpg"
            ]
        }
    },
    {
        "id": 2,
        "name": "Kertas Daur Ulang",
        "price": {
            "oldPrice": 10000,
            "newPrice": 8000
        },
        "discount": 20,
        "img": {
            "singleImage": "img/products/kerajinan/kertas daur ulang.jpg",
            "thumbs": [
                "img/products/kerajinan/kertas daur ulang.jpg",
                "img/products/kerajinan/kertas daur ulang.jpg",
                "img/products/kerajinan/kertas daur ulang.jpg"
            ]
        }
    },
    {
        "id": 3,
        "name": "Lilin Aromaterapi",
        "price": {
            "oldPrice": 8000,
            "newPrice": 7000
        },
        "discount": 10,
        "img": {
            "singleImage": "img/products/kerajinan/lilin aromaterapi.jpg",
            "thumbs": [
                "img/products/kerajinan/lilin aromaterapi.jpg",
                "img/products/kerajinan/lilin aromaterapi.jpg",
                "img/products/kerajinan/lilin aromaterapi.jpg"
            ]
        }
    },
    {
        "id": 4,
        "name": "Makrame",
        "price": {
            "oldPrice": 15000,
            "newPrice": 12000
        },
        "discount": 10,
        "img": {
            "singleImage": "img/products/kerajinan/makrame.png",
            "thumbs": [
                "img/products/kerajinan/makrame.png",
                "img/products/kerajinan/makrame.png",
                "img/products/kerajinan/makrame.png"
            ]
        }
    },
    {
        "id": 5,
        "name": "Tas Rajut",
        "price": {
            "oldPrice": 100000,
            "newPrice": 95000
        },
        "discount": 5,
        "img": {
            "singleImage": "img/products/kerajinan/tas rajut.jpeg",
            "thumbs": [
                "img/products/kerajinan/tas rajut.jpeg",
                "img/products/kerajinan/tas rajut.jpeg",
                "img/products/kerajinan/tas rajut.jpeg"
            ]
        }
    },
    {
        "id": 6,
        "name": "Tempat Tisu Dari Koran",
        "price": {
            "oldPrice": 10000,
            "newPrice": 8000
        },
        "discount": 5,
        "img": {
            "singleImage": "img/products/kerajinan/tempat tisu dari koran.jpg",
            "thumbs": [
                "img/products/kerajinan/tempat tisu dari koran.jpg",
                "img/products/kerajinan/tempat tisu dari koran.jpg",
                "img/products/kerajinan/tempat tisu dari koran.jpg"
            ]
        }
    }
]